{
    "network_id": 77,
    "network_nodes": "[Conv2DWorkload(batch=1, height=28, width=28, in_filter=512, out_filter=512, hkernel=1, wkernel=1, hpad=0, wpad=0, hstride=1, wstride=1), MaxPool2DConfig(hkernel=2, wkernel=2, hpad=0, wpad=0, hstride=2, wstride=2, ceil_mode=1), Conv2DWorkload(batch=1, height=14, width=14, in_filter=512, out_filter=112, hkernel=1, wkernel=1, hpad=0, wpad=0, hstride=1, wstride=1), ReluConfig(num_filters=112), Conv2DWorkload(batch=1, height=14, width=14, in_filter=112, out_filter=224, hkernel=3, wkernel=3, hpad=1, wpad=1, hstride=1, wstride=1)]",
    "layer_sequence": [
        "conv",
        "maxpool",
        "conv",
        "relu",
        "conv"
    ],
    "results": [
        {
            "0": {
                "samples": [
                    {
                        "write_bytes": 0,
                        "read_bytes": 48184,
                        "write_bw": 0.0,
                        "read_bw": 40.28088948336399
                    },
                    {
                        "write_bytes": 36200,
                        "read_bytes": 502144,
                        "write_bw": 25.073245738587172,
                        "read_bw": 347.80054994909165
                    },
                    {
                        "write_bytes": 39056,
                        "read_bytes": 525760,
                        "write_bw": 28.936157601890752,
                        "read_bw": 389.5297578034126
                    },
                    {
                        "write_bytes": 50176,
                        "read_bytes": 438848,
                        "write_bw": 37.08609271523178,
                        "read_bw": 324.3614001892147
                    },
                    {
                        "write_bytes": 50176,
                        "read_bytes": 502784,
                        "write_bw": 36.390272912541796,
                        "read_bw": 364.64538775628614
                    },
                    {
                        "write_bytes": 50176,
                        "read_bytes": 481408,
                        "write_bw": 34.02085621686126,
                        "read_bw": 326.4092863051408
                    },
                    {
                        "write_bytes": 50176,
                        "read_bytes": 489024,
                        "write_bw": 37.49542292200659,
                        "read_bw": 365.4368961059341
                    },
                    {
                        "write_bytes": 25088,
                        "read_bytes": 496064,
                        "write_bw": 18.522921081192827,
                        "read_bw": 366.25296250083056
                    },
                    {
                        "write_bytes": 50176,
                        "read_bytes": 506368,
                        "write_bw": 37.668821272794155,
                        "read_bw": 380.14759427340226
                    },
                    {
                        "write_bytes": 50176,
                        "read_bytes": 294144,
                        "write_bw": 33.0313882452075,
                        "read_bw": 193.63808721297661
                    },
                    {
                        "write_bytes": 0,
                        "read_bytes": 0,
                        "write_bw": 0.0,
                        "read_bw": 0.0
                    },
                    {
                        "write_bytes": 0,
                        "read_bytes": 0,
                        "write_bw": 0.0,
                        "read_bw": 0.0
                    },
                    {
                        "write_bytes": 25088,
                        "read_bytes": 410992,
                        "write_bw": 15.947418270117026,
                        "read_bw": 261.2508501941939
                    },
                    {
                        "write_bytes": 25088,
                        "read_bytes": 425472,
                        "write_bw": 17.521633154773962,
                        "read_bw": 297.1525949309625
                    },
                    {
                        "write_bytes": 28224,
                        "read_bytes": 430080,
                        "write_bw": 19.768443613288223,
                        "read_bw": 301.2334264882015
                    },
                    {
                        "write_bytes": 21952,
                        "read_bytes": 342272,
                        "write_bw": 14.944516304717817,
                        "read_bw": 233.01245830213088
                    },
                    {
                        "write_bytes": 21952,
                        "read_bytes": 254432,
                        "write_bw": 15.110236166273172,
                        "read_bw": 175.1333640787726
                    },
                    {
                        "write_bytes": 21952,
                        "read_bytes": 361088,
                        "write_bw": 15.351156301792322,
                        "read_bw": 252.5108567192778
                    },
                    {
                        "write_bytes": 21952,
                        "read_bytes": 108416,
                        "write_bw": 14.587306544751375,
                        "read_bw": 72.04343232305781
                    }
                ],
                "overall": {
                    "write_bytes": 567608,
                    "read_bytes": 6617480
                }
            },
            "1": {
                "samples": [
                    {
                        "write_bytes": 0,
                        "read_bytes": 16528,
                        "write_bw": 0.0,
                        "read_bw": 13.817087443571312
                    },
                    {
                        "write_bytes": 0,
                        "read_bytes": 0,
                        "write_bw": 0.0,
                        "read_bw": 0.0
                    },
                    {
                        "write_bytes": 0,
                        "read_bytes": 0,
                        "write_bw": 0.0,
                        "read_bw": 0.0
                    },
                    {
                        "write_bytes": 0,
                        "read_bytes": 0,
                        "write_bw": 0.0,
                        "read_bw": 0.0
                    },
                    {
                        "write_bytes": 0,
                        "read_bytes": 0,
                        "write_bw": 0.0,
                        "read_bw": 0.0
                    },
                    {
                        "write_bytes": 0,
                        "read_bytes": 0,
                        "write_bw": 0.0,
                        "read_bw": 0.0
                    },
                    {
                        "write_bytes": 0,
                        "read_bytes": 0,
                        "write_bw": 0.0,
                        "read_bw": 0.0
                    },
                    {
                        "write_bytes": 0,
                        "read_bytes": 0,
                        "write_bw": 0.0,
                        "read_bw": 0.0
                    },
                    {
                        "write_bytes": 0,
                        "read_bytes": 0,
                        "write_bw": 0.0,
                        "read_bw": 0.0
                    },
                    {
                        "write_bytes": 0,
                        "read_bytes": 0,
                        "write_bw": 0.0,
                        "read_bw": 0.0
                    },
                    {
                        "write_bytes": 0,
                        "read_bytes": 0,
                        "write_bw": 0.0,
                        "read_bw": 0.0
                    },
                    {
                        "write_bytes": 0,
                        "read_bytes": 0,
                        "write_bw": 0.0,
                        "read_bw": 0.0
                    },
                    {
                        "write_bytes": 0,
                        "read_bytes": 3168,
                        "write_bw": 0.0,
                        "read_bw": 2.0137683784969203
                    },
                    {
                        "write_bytes": 0,
                        "read_bytes": 0,
                        "write_bw": 0.0,
                        "read_bw": 0.0
                    },
                    {
                        "write_bytes": 0,
                        "read_bytes": 0,
                        "write_bw": 0.0,
                        "read_bw": 0.0
                    },
                    {
                        "write_bytes": 0,
                        "read_bytes": 0,
                        "write_bw": 0.0,
                        "read_bw": 0.0
                    },
                    {
                        "write_bytes": 0,
                        "read_bytes": 2736,
                        "write_bw": 0.0,
                        "read_bw": 1.8832728749509564
                    },
                    {
                        "write_bytes": 0,
                        "read_bytes": 0,
                        "write_bw": 0.0,
                        "read_bw": 0.0
                    },
                    {
                        "write_bytes": 0,
                        "read_bytes": 0,
                        "write_bw": 0.0,
                        "read_bw": 0.0
                    }
                ],
                "overall": {
                    "write_bytes": 0,
                    "read_bytes": 22432
                }
            },
            "2": {
                "samples": [
                    {
                        "write_bytes": 0,
                        "read_bytes": 31232,
                        "write_bw": 0.0,
                        "read_bw": 26.1093462631667
                    },
                    {
                        "write_bytes": 0,
                        "read_bytes": 501120,
                        "write_bw": 0.0,
                        "read_bw": 347.0912957049946
                    },
                    {
                        "write_bytes": 0,
                        "read_bytes": 525248,
                        "write_bw": 0.0,
                        "read_bw": 389.15042267712806
                    },
                    {
                        "write_bytes": 0,
                        "read_bytes": 437824,
                        "write_bw": 0.0,
                        "read_bw": 323.60454115421
                    },
                    {
                        "write_bytes": 0,
                        "read_bytes": 501888,
                        "write_bw": 0.0,
                        "read_bw": 363.99556145427647
                    },
                    {
                        "write_bytes": 0,
                        "read_bytes": 480384,
                        "write_bw": 0.0,
                        "read_bw": 325.71498311704164
                    },
                    {
                        "write_bytes": 0,
                        "read_bytes": 488000,
                        "write_bw": 0.0,
                        "read_bw": 364.67168339324013
                    },
                    {
                        "write_bytes": 0,
                        "read_bytes": 495296,
                        "write_bw": 0.0,
                        "read_bw": 365.68593430446754
                    },
                    {
                        "write_bytes": 0,
                        "read_bytes": 505600,
                        "write_bw": 0.0,
                        "read_bw": 379.57103068249216
                    },
                    {
                        "write_bytes": 0,
                        "read_bytes": 293120,
                        "write_bw": 0.0,
                        "read_bw": 192.96397724878872
                    },
                    {
                        "write_bytes": 0,
                        "read_bytes": 0,
                        "write_bw": 0.0,
                        "read_bw": 0.0
                    },
                    {
                        "write_bytes": 0,
                        "read_bytes": 0,
                        "write_bw": 0.0,
                        "read_bw": 0.0
                    },
                    {
                        "write_bytes": 0,
                        "read_bytes": 0,
                        "write_bw": 0.0,
                        "read_bw": 0.0
                    },
                    {
                        "write_bytes": 0,
                        "read_bytes": 0,
                        "write_bw": 0.0,
                        "read_bw": 0.0
                    },
                    {
                        "write_bytes": 0,
                        "read_bytes": 0,
                        "write_bw": 0.0,
                        "read_bw": 0.0
                    },
                    {
                        "write_bytes": 0,
                        "read_bytes": 0,
                        "write_bw": 0.0,
                        "read_bw": 0.0
                    },
                    {
                        "write_bytes": 0,
                        "read_bytes": 248960,
                        "write_bw": 0.0,
                        "read_bw": 171.36681832887066
                    },
                    {
                        "write_bytes": 0,
                        "read_bytes": 360320,
                        "write_bw": 0.0,
                        "read_bw": 251.9737900265037
                    },
                    {
                        "write_bytes": 0,
                        "read_bytes": 107520,
                        "write_bw": 0.0,
                        "read_bw": 71.4480320559251
                    }
                ],
                "overall": {
                    "write_bytes": 0,
                    "read_bytes": 4976512
                }
            },
            "3": {
                "samples": [
                    {
                        "write_bytes": 0,
                        "read_bytes": 296,
                        "write_bw": 0.0,
                        "read_bw": 0.24745025915398766
                    },
                    {
                        "write_bytes": 0,
                        "read_bytes": 0,
                        "write_bw": 0.0,
                        "read_bw": 0.0
                    },
                    {
                        "write_bytes": 0,
                        "read_bytes": 0,
                        "write_bw": 0.0,
                        "read_bw": 0.0
                    },
                    {
                        "write_bytes": 0,
                        "read_bytes": 0,
                        "write_bw": 0.0,
                        "read_bw": 0.0
                    },
                    {
                        "write_bytes": 0,
                        "read_bytes": 0,
                        "write_bw": 0.0,
                        "read_bw": 0.0
                    },
                    {
                        "write_bytes": 0,
                        "read_bytes": 0,
                        "write_bw": 0.0,
                        "read_bw": 0.0
                    },
                    {
                        "write_bytes": 0,
                        "read_bytes": 0,
                        "write_bw": 0.0,
                        "read_bw": 0.0
                    },
                    {
                        "write_bytes": 0,
                        "read_bytes": 0,
                        "write_bw": 0.0,
                        "read_bw": 0.0
                    },
                    {
                        "write_bytes": 0,
                        "read_bytes": 0,
                        "write_bw": 0.0,
                        "read_bw": 0.0
                    },
                    {
                        "write_bytes": 0,
                        "read_bytes": 0,
                        "write_bw": 0.0,
                        "read_bw": 0.0
                    },
                    {
                        "write_bytes": 0,
                        "read_bytes": 0,
                        "write_bw": 0.0,
                        "read_bw": 0.0
                    },
                    {
                        "write_bytes": 0,
                        "read_bytes": 0,
                        "write_bw": 0.0,
                        "read_bw": 0.0
                    },
                    {
                        "write_bytes": 0,
                        "read_bytes": 16,
                        "write_bw": 0.0,
                        "read_bw": 0.010170547366146063
                    },
                    {
                        "write_bytes": 0,
                        "read_bytes": 0,
                        "write_bw": 0.0,
                        "read_bw": 0.0
                    },
                    {
                        "write_bytes": 0,
                        "read_bytes": 0,
                        "write_bw": 0.0,
                        "read_bw": 0.0
                    },
                    {
                        "write_bytes": 0,
                        "read_bytes": 0,
                        "write_bw": 0.0,
                        "read_bw": 0.0
                    },
                    {
                        "write_bytes": 0,
                        "read_bytes": 1712,
                        "write_bw": 0.0,
                        "read_bw": 1.1784222083026452
                    },
                    {
                        "write_bytes": 0,
                        "read_bytes": 0,
                        "write_bw": 0.0,
                        "read_bw": 0.0
                    },
                    {
                        "write_bytes": 0,
                        "read_bytes": 0,
                        "write_bw": 0.0,
                        "read_bw": 0.0
                    }
                ],
                "overall": {
                    "write_bytes": 0,
                    "read_bytes": 2024
                }
            },
            "4": {
                "samples": [
                    {
                        "write_bytes": 0,
                        "read_bytes": 0,
                        "write_bw": 0.0,
                        "read_bw": 0.0
                    },
                    {
                        "write_bytes": 0,
                        "read_bytes": 1024,
                        "write_bw": 0.0,
                        "read_bw": 0.7092542440970515
                    },
                    {
                        "write_bytes": 0,
                        "read_bytes": 512,
                        "write_bw": 0.0,
                        "read_bw": 0.3793351262845162
                    },
                    {
                        "write_bytes": 0,
                        "read_bytes": 1024,
                        "write_bw": 0.0,
                        "read_bw": 0.7568590350047302
                    },
                    {
                        "write_bytes": 0,
                        "read_bytes": 1024,
                        "write_bw": 0.0,
                        "read_bw": 0.7426586308681999
                    },
                    {
                        "write_bytes": 0,
                        "read_bytes": 1024,
                        "write_bw": 0.0,
                        "read_bw": 0.6943031880992094
                    },
                    {
                        "write_bytes": 0,
                        "read_bytes": 1024,
                        "write_bw": 0.0,
                        "read_bw": 0.765212712694012
                    },
                    {
                        "write_bytes": 0,
                        "read_bytes": 768,
                        "write_bw": 0.0,
                        "read_bw": 0.5670281963630457
                    },
                    {
                        "write_bytes": 0,
                        "read_bytes": 768,
                        "write_bw": 0.0,
                        "read_bw": 0.5765635909101147
                    },
                    {
                        "write_bytes": 0,
                        "read_bytes": 1024,
                        "write_bw": 0.0,
                        "read_bw": 0.6741099641879081
                    },
                    {
                        "write_bytes": 0,
                        "read_bytes": 0,
                        "write_bw": 0.0,
                        "read_bw": 0.0
                    },
                    {
                        "write_bytes": 0,
                        "read_bytes": 0,
                        "write_bw": 0.0,
                        "read_bw": 0.0
                    },
                    {
                        "write_bytes": 0,
                        "read_bytes": 407808,
                        "write_bw": 0.0,
                        "read_bw": 259.22691126833087
                    },
                    {
                        "write_bytes": 0,
                        "read_bytes": 425472,
                        "write_bw": 0.0,
                        "read_bw": 297.1525949309625
                    },
                    {
                        "write_bytes": 0,
                        "read_bytes": 430080,
                        "write_bw": 0.0,
                        "read_bw": 301.2334264882015
                    },
                    {
                        "write_bytes": 0,
                        "read_bytes": 342272,
                        "write_bw": 0.0,
                        "read_bw": 233.01245830213088
                    },
                    {
                        "write_bytes": 0,
                        "read_bytes": 896,
                        "write_bw": 0.0,
                        "read_bw": 0.6167443333172723
                    },
                    {
                        "write_bytes": 0,
                        "read_bytes": 896,
                        "write_bw": 0.0,
                        "read_bw": 0.6265778082364213
                    },
                    {
                        "write_bytes": 0,
                        "read_bytes": 896,
                        "write_bw": 0.0,
                        "read_bw": 0.5954002671327092
                    }
                ],
                "overall": {
                    "write_bytes": 0,
                    "read_bytes": 1616512
                }
            },
            "5": {
                "samples": [
                    {
                        "write_bytes": 0,
                        "read_bytes": 0,
                        "write_bw": 0.0,
                        "read_bw": 0.0
                    },
                    {
                        "write_bytes": 36288,
                        "read_bytes": 0,
                        "write_bw": 25.134197275189262,
                        "read_bw": 0.0
                    },
                    {
                        "write_bytes": 38968,
                        "read_bytes": 0,
                        "write_bw": 28.8709593770606,
                        "read_bw": 0.0
                    },
                    {
                        "write_bytes": 50176,
                        "read_bytes": 0,
                        "write_bw": 37.08609271523178,
                        "read_bw": 0.0
                    },
                    {
                        "write_bytes": 50176,
                        "read_bytes": 0,
                        "write_bw": 36.390272912541796,
                        "read_bw": 0.0
                    },
                    {
                        "write_bytes": 50176,
                        "read_bytes": 0,
                        "write_bw": 34.02085621686126,
                        "read_bw": 0.0
                    },
                    {
                        "write_bytes": 50176,
                        "read_bytes": 0,
                        "write_bw": 37.49542292200659,
                        "read_bw": 0.0
                    },
                    {
                        "write_bytes": 25088,
                        "read_bytes": 0,
                        "write_bw": 18.522921081192827,
                        "read_bw": 0.0
                    },
                    {
                        "write_bytes": 50176,
                        "read_bytes": 0,
                        "write_bw": 37.668821272794155,
                        "read_bw": 0.0
                    },
                    {
                        "write_bytes": 50176,
                        "read_bytes": 0,
                        "write_bw": 33.0313882452075,
                        "read_bw": 0.0
                    },
                    {
                        "write_bytes": 0,
                        "read_bytes": 0,
                        "write_bw": 0.0,
                        "read_bw": 0.0
                    },
                    {
                        "write_bytes": 0,
                        "read_bytes": 0,
                        "write_bw": 0.0,
                        "read_bw": 0.0
                    },
                    {
                        "write_bytes": 25088,
                        "read_bytes": 0,
                        "write_bw": 15.947418270117026,
                        "read_bw": 0.0
                    },
                    {
                        "write_bytes": 25088,
                        "read_bytes": 0,
                        "write_bw": 17.521633154773962,
                        "read_bw": 0.0
                    },
                    {
                        "write_bytes": 28224,
                        "read_bytes": 0,
                        "write_bw": 19.768443613288223,
                        "read_bw": 0.0
                    },
                    {
                        "write_bytes": 21952,
                        "read_bytes": 0,
                        "write_bw": 14.944516304717817,
                        "read_bw": 0.0
                    },
                    {
                        "write_bytes": 21952,
                        "read_bytes": 0,
                        "write_bw": 15.110236166273172,
                        "read_bw": 0.0
                    },
                    {
                        "write_bytes": 21952,
                        "read_bytes": 0,
                        "write_bw": 15.351156301792322,
                        "read_bw": 0.0
                    },
                    {
                        "write_bytes": 21952,
                        "read_bytes": 0,
                        "write_bw": 14.587306544751375,
                        "read_bw": 0.0
                    }
                ],
                "overall": {
                    "write_bytes": 567608,
                    "read_bytes": 0
                }
            },
            "total_samples": 19
        },
        {
            "0": {
                "samples": [
                    {
                        "write_bytes": 0,
                        "read_bytes": 48184,
                        "write_bw": 0.0,
                        "read_bw": 40.28088948336399
                    },
                    {
                        "write_bytes": 36200,
                        "read_bytes": 502144,
                        "write_bw": 25.073245738587172,
                        "read_bw": 347.80054994909165
                    },
                    {
                        "write_bytes": 39056,
                        "read_bytes": 525760,
                        "write_bw": 28.936157601890752,
                        "read_bw": 389.5297578034126
                    },
                    {
                        "write_bytes": 50176,
                        "read_bytes": 438848,
                        "write_bw": 37.08609271523178,
                        "read_bw": 324.3614001892147
                    },
                    {
                        "write_bytes": 50176,
                        "read_bytes": 502784,
                        "write_bw": 36.390272912541796,
                        "read_bw": 364.64538775628614
                    },
                    {
                        "write_bytes": 50176,
                        "read_bytes": 481408,
                        "write_bw": 34.02085621686126,
                        "read_bw": 326.4092863051408
                    },
                    {
                        "write_bytes": 50176,
                        "read_bytes": 489024,
                        "write_bw": 37.49542292200659,
                        "read_bw": 365.4368961059341
                    },
                    {
                        "write_bytes": 25088,
                        "read_bytes": 496064,
                        "write_bw": 18.522921081192827,
                        "read_bw": 366.25296250083056
                    },
                    {
                        "write_bytes": 50176,
                        "read_bytes": 506368,
                        "write_bw": 37.668821272794155,
                        "read_bw": 380.14759427340226
                    },
                    {
                        "write_bytes": 50176,
                        "read_bytes": 294144,
                        "write_bw": 33.0313882452075,
                        "read_bw": 193.63808721297661
                    },
                    {
                        "write_bytes": 0,
                        "read_bytes": 0,
                        "write_bw": 0.0,
                        "read_bw": 0.0
                    },
                    {
                        "write_bytes": 0,
                        "read_bytes": 0,
                        "write_bw": 0.0,
                        "read_bw": 0.0
                    },
                    {
                        "write_bytes": 25088,
                        "read_bytes": 410992,
                        "write_bw": 15.947418270117026,
                        "read_bw": 261.2508501941939
                    },
                    {
                        "write_bytes": 25088,
                        "read_bytes": 425472,
                        "write_bw": 17.521633154773962,
                        "read_bw": 297.1525949309625
                    },
                    {
                        "write_bytes": 28224,
                        "read_bytes": 430080,
                        "write_bw": 19.768443613288223,
                        "read_bw": 301.2334264882015
                    },
                    {
                        "write_bytes": 21952,
                        "read_bytes": 342272,
                        "write_bw": 14.944516304717817,
                        "read_bw": 233.01245830213088
                    },
                    {
                        "write_bytes": 21952,
                        "read_bytes": 254432,
                        "write_bw": 15.110236166273172,
                        "read_bw": 175.1333640787726
                    },
                    {
                        "write_bytes": 21952,
                        "read_bytes": 361088,
                        "write_bw": 15.351156301792322,
                        "read_bw": 252.5108567192778
                    },
                    {
                        "write_bytes": 21952,
                        "read_bytes": 108416,
                        "write_bw": 14.587306544751375,
                        "read_bw": 72.04343232305781
                    }
                ],
                "overall": {
                    "write_bytes": 567608,
                    "read_bytes": 6617480
                }
            },
            "1": {
                "samples": [
                    {
                        "write_bytes": 0,
                        "read_bytes": 16528,
                        "write_bw": 0.0,
                        "read_bw": 13.817087443571312
                    },
                    {
                        "write_bytes": 0,
                        "read_bytes": 0,
                        "write_bw": 0.0,
                        "read_bw": 0.0
                    },
                    {
                        "write_bytes": 0,
                        "read_bytes": 0,
                        "write_bw": 0.0,
                        "read_bw": 0.0
                    },
                    {
                        "write_bytes": 0,
                        "read_bytes": 0,
                        "write_bw": 0.0,
                        "read_bw": 0.0
                    },
                    {
                        "write_bytes": 0,
                        "read_bytes": 0,
                        "write_bw": 0.0,
                        "read_bw": 0.0
                    },
                    {
                        "write_bytes": 0,
                        "read_bytes": 0,
                        "write_bw": 0.0,
                        "read_bw": 0.0
                    },
                    {
                        "write_bytes": 0,
                        "read_bytes": 0,
                        "write_bw": 0.0,
                        "read_bw": 0.0
                    },
                    {
                        "write_bytes": 0,
                        "read_bytes": 0,
                        "write_bw": 0.0,
                        "read_bw": 0.0
                    },
                    {
                        "write_bytes": 0,
                        "read_bytes": 0,
                        "write_bw": 0.0,
                        "read_bw": 0.0
                    },
                    {
                        "write_bytes": 0,
                        "read_bytes": 0,
                        "write_bw": 0.0,
                        "read_bw": 0.0
                    },
                    {
                        "write_bytes": 0,
                        "read_bytes": 0,
                        "write_bw": 0.0,
                        "read_bw": 0.0
                    },
                    {
                        "write_bytes": 0,
                        "read_bytes": 0,
                        "write_bw": 0.0,
                        "read_bw": 0.0
                    },
                    {
                        "write_bytes": 0,
                        "read_bytes": 3168,
                        "write_bw": 0.0,
                        "read_bw": 2.0137683784969203
                    },
                    {
                        "write_bytes": 0,
                        "read_bytes": 0,
                        "write_bw": 0.0,
                        "read_bw": 0.0
                    },
                    {
                        "write_bytes": 0,
                        "read_bytes": 0,
                        "write_bw": 0.0,
                        "read_bw": 0.0
                    },
                    {
                        "write_bytes": 0,
                        "read_bytes": 0,
                        "write_bw": 0.0,
                        "read_bw": 0.0
                    },
                    {
                        "write_bytes": 0,
                        "read_bytes": 2736,
                        "write_bw": 0.0,
                        "read_bw": 1.8832728749509564
                    },
                    {
                        "write_bytes": 0,
                        "read_bytes": 0,
                        "write_bw": 0.0,
                        "read_bw": 0.0
                    },
                    {
                        "write_bytes": 0,
                        "read_bytes": 0,
                        "write_bw": 0.0,
                        "read_bw": 0.0
                    }
                ],
                "overall": {
                    "write_bytes": 0,
                    "read_bytes": 22432
                }
            },
            "2": {
                "samples": [
                    {
                        "write_bytes": 0,
                        "read_bytes": 31232,
                        "write_bw": 0.0,
                        "read_bw": 26.1093462631667
                    },
                    {
                        "write_bytes": 0,
                        "read_bytes": 501120,
                        "write_bw": 0.0,
                        "read_bw": 347.0912957049946
                    },
                    {
                        "write_bytes": 0,
                        "read_bytes": 525248,
                        "write_bw": 0.0,
                        "read_bw": 389.15042267712806
                    },
                    {
                        "write_bytes": 0,
                        "read_bytes": 437824,
                        "write_bw": 0.0,
                        "read_bw": 323.60454115421
                    },
                    {
                        "write_bytes": 0,
                        "read_bytes": 501888,
                        "write_bw": 0.0,
                        "read_bw": 363.99556145427647
                    },
                    {
                        "write_bytes": 0,
                        "read_bytes": 480384,
                        "write_bw": 0.0,
                        "read_bw": 325.71498311704164
                    },
                    {
                        "write_bytes": 0,
                        "read_bytes": 488000,
                        "write_bw": 0.0,
                        "read_bw": 364.67168339324013
                    },
                    {
                        "write_bytes": 0,
                        "read_bytes": 495296,
                        "write_bw": 0.0,
                        "read_bw": 365.68593430446754
                    },
                    {
                        "write_bytes": 0,
                        "read_bytes": 505600,
                        "write_bw": 0.0,
                        "read_bw": 379.57103068249216
                    },
                    {
                        "write_bytes": 0,
                        "read_bytes": 293120,
                        "write_bw": 0.0,
                        "read_bw": 192.96397724878872
                    },
                    {
                        "write_bytes": 0,
                        "read_bytes": 0,
                        "write_bw": 0.0,
                        "read_bw": 0.0
                    },
                    {
                        "write_bytes": 0,
                        "read_bytes": 0,
                        "write_bw": 0.0,
                        "read_bw": 0.0
                    },
                    {
                        "write_bytes": 0,
                        "read_bytes": 0,
                        "write_bw": 0.0,
                        "read_bw": 0.0
                    },
                    {
                        "write_bytes": 0,
                        "read_bytes": 0,
                        "write_bw": 0.0,
                        "read_bw": 0.0
                    },
                    {
                        "write_bytes": 0,
                        "read_bytes": 0,
                        "write_bw": 0.0,
                        "read_bw": 0.0
                    },
                    {
                        "write_bytes": 0,
                        "read_bytes": 0,
                        "write_bw": 0.0,
                        "read_bw": 0.0
                    },
                    {
                        "write_bytes": 0,
                        "read_bytes": 248960,
                        "write_bw": 0.0,
                        "read_bw": 171.36681832887066
                    },
                    {
                        "write_bytes": 0,
                        "read_bytes": 360320,
                        "write_bw": 0.0,
                        "read_bw": 251.9737900265037
                    },
                    {
                        "write_bytes": 0,
                        "read_bytes": 107520,
                        "write_bw": 0.0,
                        "read_bw": 71.4480320559251
                    }
                ],
                "overall": {
                    "write_bytes": 0,
                    "read_bytes": 4976512
                }
            },
            "3": {
                "samples": [
                    {
                        "write_bytes": 0,
                        "read_bytes": 296,
                        "write_bw": 0.0,
                        "read_bw": 0.24745025915398766
                    },
                    {
                        "write_bytes": 0,
                        "read_bytes": 0,
                        "write_bw": 0.0,
                        "read_bw": 0.0
                    },
                    {
                        "write_bytes": 0,
                        "read_bytes": 0,
                        "write_bw": 0.0,
                        "read_bw": 0.0
                    },
                    {
                        "write_bytes": 0,
                        "read_bytes": 0,
                        "write_bw": 0.0,
                        "read_bw": 0.0
                    },
                    {
                        "write_bytes": 0,
                        "read_bytes": 0,
                        "write_bw": 0.0,
                        "read_bw": 0.0
                    },
                    {
                        "write_bytes": 0,
                        "read_bytes": 0,
                        "write_bw": 0.0,
                        "read_bw": 0.0
                    },
                    {
                        "write_bytes": 0,
                        "read_bytes": 0,
                        "write_bw": 0.0,
                        "read_bw": 0.0
                    },
                    {
                        "write_bytes": 0,
                        "read_bytes": 0,
                        "write_bw": 0.0,
                        "read_bw": 0.0
                    },
                    {
                        "write_bytes": 0,
                        "read_bytes": 0,
                        "write_bw": 0.0,
                        "read_bw": 0.0
                    },
                    {
                        "write_bytes": 0,
                        "read_bytes": 0,
                        "write_bw": 0.0,
                        "read_bw": 0.0
                    },
                    {
                        "write_bytes": 0,
                        "read_bytes": 0,
                        "write_bw": 0.0,
                        "read_bw": 0.0
                    },
                    {
                        "write_bytes": 0,
                        "read_bytes": 0,
                        "write_bw": 0.0,
                        "read_bw": 0.0
                    },
                    {
                        "write_bytes": 0,
                        "read_bytes": 16,
                        "write_bw": 0.0,
                        "read_bw": 0.010170547366146063
                    },
                    {
                        "write_bytes": 0,
                        "read_bytes": 0,
                        "write_bw": 0.0,
                        "read_bw": 0.0
                    },
                    {
                        "write_bytes": 0,
                        "read_bytes": 0,
                        "write_bw": 0.0,
                        "read_bw": 0.0
                    },
                    {
                        "write_bytes": 0,
                        "read_bytes": 0,
                        "write_bw": 0.0,
                        "read_bw": 0.0
                    },
                    {
                        "write_bytes": 0,
                        "read_bytes": 1712,
                        "write_bw": 0.0,
                        "read_bw": 1.1784222083026452
                    },
                    {
                        "write_bytes": 0,
                        "read_bytes": 0,
                        "write_bw": 0.0,
                        "read_bw": 0.0
                    },
                    {
                        "write_bytes": 0,
                        "read_bytes": 0,
                        "write_bw": 0.0,
                        "read_bw": 0.0
                    }
                ],
                "overall": {
                    "write_bytes": 0,
                    "read_bytes": 2024
                }
            },
            "4": {
                "samples": [
                    {
                        "write_bytes": 0,
                        "read_bytes": 0,
                        "write_bw": 0.0,
                        "read_bw": 0.0
                    },
                    {
                        "write_bytes": 0,
                        "read_bytes": 1024,
                        "write_bw": 0.0,
                        "read_bw": 0.7092542440970515
                    },
                    {
                        "write_bytes": 0,
                        "read_bytes": 512,
                        "write_bw": 0.0,
                        "read_bw": 0.3793351262845162
                    },
                    {
                        "write_bytes": 0,
                        "read_bytes": 1024,
                        "write_bw": 0.0,
                        "read_bw": 0.7568590350047302
                    },
                    {
                        "write_bytes": 0,
                        "read_bytes": 1024,
                        "write_bw": 0.0,
                        "read_bw": 0.7426586308681999
                    },
                    {
                        "write_bytes": 0,
                        "read_bytes": 1024,
                        "write_bw": 0.0,
                        "read_bw": 0.6943031880992094
                    },
                    {
                        "write_bytes": 0,
                        "read_bytes": 1024,
                        "write_bw": 0.0,
                        "read_bw": 0.765212712694012
                    },
                    {
                        "write_bytes": 0,
                        "read_bytes": 768,
                        "write_bw": 0.0,
                        "read_bw": 0.5670281963630457
                    },
                    {
                        "write_bytes": 0,
                        "read_bytes": 768,
                        "write_bw": 0.0,
                        "read_bw": 0.5765635909101147
                    },
                    {
                        "write_bytes": 0,
                        "read_bytes": 1024,
                        "write_bw": 0.0,
                        "read_bw": 0.6741099641879081
                    },
                    {
                        "write_bytes": 0,
                        "read_bytes": 0,
                        "write_bw": 0.0,
                        "read_bw": 0.0
                    },
                    {
                        "write_bytes": 0,
                        "read_bytes": 0,
                        "write_bw": 0.0,
                        "read_bw": 0.0
                    },
                    {
                        "write_bytes": 0,
                        "read_bytes": 407808,
                        "write_bw": 0.0,
                        "read_bw": 259.22691126833087
                    },
                    {
                        "write_bytes": 0,
                        "read_bytes": 425472,
                        "write_bw": 0.0,
                        "read_bw": 297.1525949309625
                    },
                    {
                        "write_bytes": 0,
                        "read_bytes": 430080,
                        "write_bw": 0.0,
                        "read_bw": 301.2334264882015
                    },
                    {
                        "write_bytes": 0,
                        "read_bytes": 342272,
                        "write_bw": 0.0,
                        "read_bw": 233.01245830213088
                    },
                    {
                        "write_bytes": 0,
                        "read_bytes": 896,
                        "write_bw": 0.0,
                        "read_bw": 0.6167443333172723
                    },
                    {
                        "write_bytes": 0,
                        "read_bytes": 896,
                        "write_bw": 0.0,
                        "read_bw": 0.6265778082364213
                    },
                    {
                        "write_bytes": 0,
                        "read_bytes": 896,
                        "write_bw": 0.0,
                        "read_bw": 0.5954002671327092
                    }
                ],
                "overall": {
                    "write_bytes": 0,
                    "read_bytes": 1616512
                }
            },
            "5": {
                "samples": [
                    {
                        "write_bytes": 0,
                        "read_bytes": 0,
                        "write_bw": 0.0,
                        "read_bw": 0.0
                    },
                    {
                        "write_bytes": 36288,
                        "read_bytes": 0,
                        "write_bw": 25.134197275189262,
                        "read_bw": 0.0
                    },
                    {
                        "write_bytes": 38968,
                        "read_bytes": 0,
                        "write_bw": 28.8709593770606,
                        "read_bw": 0.0
                    },
                    {
                        "write_bytes": 50176,
                        "read_bytes": 0,
                        "write_bw": 37.08609271523178,
                        "read_bw": 0.0
                    },
                    {
                        "write_bytes": 50176,
                        "read_bytes": 0,
                        "write_bw": 36.390272912541796,
                        "read_bw": 0.0
                    },
                    {
                        "write_bytes": 50176,
                        "read_bytes": 0,
                        "write_bw": 34.02085621686126,
                        "read_bw": 0.0
                    },
                    {
                        "write_bytes": 50176,
                        "read_bytes": 0,
                        "write_bw": 37.49542292200659,
                        "read_bw": 0.0
                    },
                    {
                        "write_bytes": 25088,
                        "read_bytes": 0,
                        "write_bw": 18.522921081192827,
                        "read_bw": 0.0
                    },
                    {
                        "write_bytes": 50176,
                        "read_bytes": 0,
                        "write_bw": 37.668821272794155,
                        "read_bw": 0.0
                    },
                    {
                        "write_bytes": 50176,
                        "read_bytes": 0,
                        "write_bw": 33.0313882452075,
                        "read_bw": 0.0
                    },
                    {
                        "write_bytes": 0,
                        "read_bytes": 0,
                        "write_bw": 0.0,
                        "read_bw": 0.0
                    },
                    {
                        "write_bytes": 0,
                        "read_bytes": 0,
                        "write_bw": 0.0,
                        "read_bw": 0.0
                    },
                    {
                        "write_bytes": 25088,
                        "read_bytes": 0,
                        "write_bw": 15.947418270117026,
                        "read_bw": 0.0
                    },
                    {
                        "write_bytes": 25088,
                        "read_bytes": 0,
                        "write_bw": 17.521633154773962,
                        "read_bw": 0.0
                    },
                    {
                        "write_bytes": 28224,
                        "read_bytes": 0,
                        "write_bw": 19.768443613288223,
                        "read_bw": 0.0
                    },
                    {
                        "write_bytes": 21952,
                        "read_bytes": 0,
                        "write_bw": 14.944516304717817,
                        "read_bw": 0.0
                    },
                    {
                        "write_bytes": 21952,
                        "read_bytes": 0,
                        "write_bw": 15.110236166273172,
                        "read_bw": 0.0
                    },
                    {
                        "write_bytes": 21952,
                        "read_bytes": 0,
                        "write_bw": 15.351156301792322,
                        "read_bw": 0.0
                    },
                    {
                        "write_bytes": 21952,
                        "read_bytes": 0,
                        "write_bw": 14.587306544751375,
                        "read_bw": 0.0
                    }
                ],
                "overall": {
                    "write_bytes": 567608,
                    "read_bytes": 0
                }
            },
            "total_samples": 19
        },
        {
            "0": {
                "samples": [
                    {
                        "write_bytes": 0,
                        "read_bytes": 48184,
                        "write_bw": 0.0,
                        "read_bw": 40.28088948336399
                    },
                    {
                        "write_bytes": 36200,
                        "read_bytes": 502144,
                        "write_bw": 25.073245738587172,
                        "read_bw": 347.80054994909165
                    },
                    {
                        "write_bytes": 39056,
                        "read_bytes": 525760,
                        "write_bw": 28.936157601890752,
                        "read_bw": 389.5297578034126
                    },
                    {
                        "write_bytes": 50176,
                        "read_bytes": 438848,
                        "write_bw": 37.08609271523178,
                        "read_bw": 324.3614001892147
                    },
                    {
                        "write_bytes": 50176,
                        "read_bytes": 502784,
                        "write_bw": 36.390272912541796,
                        "read_bw": 364.64538775628614
                    },
                    {
                        "write_bytes": 50176,
                        "read_bytes": 481408,
                        "write_bw": 34.02085621686126,
                        "read_bw": 326.4092863051408
                    },
                    {
                        "write_bytes": 50176,
                        "read_bytes": 489024,
                        "write_bw": 37.49542292200659,
                        "read_bw": 365.4368961059341
                    },
                    {
                        "write_bytes": 25088,
                        "read_bytes": 496064,
                        "write_bw": 18.522921081192827,
                        "read_bw": 366.25296250083056
                    },
                    {
                        "write_bytes": 50176,
                        "read_bytes": 506368,
                        "write_bw": 37.668821272794155,
                        "read_bw": 380.14759427340226
                    },
                    {
                        "write_bytes": 50176,
                        "read_bytes": 294144,
                        "write_bw": 33.0313882452075,
                        "read_bw": 193.63808721297661
                    },
                    {
                        "write_bytes": 0,
                        "read_bytes": 0,
                        "write_bw": 0.0,
                        "read_bw": 0.0
                    },
                    {
                        "write_bytes": 0,
                        "read_bytes": 0,
                        "write_bw": 0.0,
                        "read_bw": 0.0
                    },
                    {
                        "write_bytes": 25088,
                        "read_bytes": 410992,
                        "write_bw": 15.947418270117026,
                        "read_bw": 261.2508501941939
                    },
                    {
                        "write_bytes": 25088,
                        "read_bytes": 425472,
                        "write_bw": 17.521633154773962,
                        "read_bw": 297.1525949309625
                    },
                    {
                        "write_bytes": 28224,
                        "read_bytes": 430080,
                        "write_bw": 19.768443613288223,
                        "read_bw": 301.2334264882015
                    },
                    {
                        "write_bytes": 21952,
                        "read_bytes": 342272,
                        "write_bw": 14.944516304717817,
                        "read_bw": 233.01245830213088
                    },
                    {
                        "write_bytes": 21952,
                        "read_bytes": 254432,
                        "write_bw": 15.110236166273172,
                        "read_bw": 175.1333640787726
                    },
                    {
                        "write_bytes": 21952,
                        "read_bytes": 361088,
                        "write_bw": 15.351156301792322,
                        "read_bw": 252.5108567192778
                    },
                    {
                        "write_bytes": 21952,
                        "read_bytes": 108416,
                        "write_bw": 14.587306544751375,
                        "read_bw": 72.04343232305781
                    }
                ],
                "overall": {
                    "write_bytes": 567608,
                    "read_bytes": 6617480
                }
            },
            "1": {
                "samples": [
                    {
                        "write_bytes": 0,
                        "read_bytes": 16528,
                        "write_bw": 0.0,
                        "read_bw": 13.817087443571312
                    },
                    {
                        "write_bytes": 0,
                        "read_bytes": 0,
                        "write_bw": 0.0,
                        "read_bw": 0.0
                    },
                    {
                        "write_bytes": 0,
                        "read_bytes": 0,
                        "write_bw": 0.0,
                        "read_bw": 0.0
                    },
                    {
                        "write_bytes": 0,
                        "read_bytes": 0,
                        "write_bw": 0.0,
                        "read_bw": 0.0
                    },
                    {
                        "write_bytes": 0,
                        "read_bytes": 0,
                        "write_bw": 0.0,
                        "read_bw": 0.0
                    },
                    {
                        "write_bytes": 0,
                        "read_bytes": 0,
                        "write_bw": 0.0,
                        "read_bw": 0.0
                    },
                    {
                        "write_bytes": 0,
                        "read_bytes": 0,
                        "write_bw": 0.0,
                        "read_bw": 0.0
                    },
                    {
                        "write_bytes": 0,
                        "read_bytes": 0,
                        "write_bw": 0.0,
                        "read_bw": 0.0
                    },
                    {
                        "write_bytes": 0,
                        "read_bytes": 0,
                        "write_bw": 0.0,
                        "read_bw": 0.0
                    },
                    {
                        "write_bytes": 0,
                        "read_bytes": 0,
                        "write_bw": 0.0,
                        "read_bw": 0.0
                    },
                    {
                        "write_bytes": 0,
                        "read_bytes": 0,
                        "write_bw": 0.0,
                        "read_bw": 0.0
                    },
                    {
                        "write_bytes": 0,
                        "read_bytes": 0,
                        "write_bw": 0.0,
                        "read_bw": 0.0
                    },
                    {
                        "write_bytes": 0,
                        "read_bytes": 3168,
                        "write_bw": 0.0,
                        "read_bw": 2.0137683784969203
                    },
                    {
                        "write_bytes": 0,
                        "read_bytes": 0,
                        "write_bw": 0.0,
                        "read_bw": 0.0
                    },
                    {
                        "write_bytes": 0,
                        "read_bytes": 0,
                        "write_bw": 0.0,
                        "read_bw": 0.0
                    },
                    {
                        "write_bytes": 0,
                        "read_bytes": 0,
                        "write_bw": 0.0,
                        "read_bw": 0.0
                    },
                    {
                        "write_bytes": 0,
                        "read_bytes": 2736,
                        "write_bw": 0.0,
                        "read_bw": 1.8832728749509564
                    },
                    {
                        "write_bytes": 0,
                        "read_bytes": 0,
                        "write_bw": 0.0,
                        "read_bw": 0.0
                    },
                    {
                        "write_bytes": 0,
                        "read_bytes": 0,
                        "write_bw": 0.0,
                        "read_bw": 0.0
                    }
                ],
                "overall": {
                    "write_bytes": 0,
                    "read_bytes": 22432
                }
            },
            "2": {
                "samples": [
                    {
                        "write_bytes": 0,
                        "read_bytes": 31232,
                        "write_bw": 0.0,
                        "read_bw": 26.1093462631667
                    },
                    {
                        "write_bytes": 0,
                        "read_bytes": 501120,
                        "write_bw": 0.0,
                        "read_bw": 347.0912957049946
                    },
                    {
                        "write_bytes": 0,
                        "read_bytes": 525248,
                        "write_bw": 0.0,
                        "read_bw": 389.15042267712806
                    },
                    {
                        "write_bytes": 0,
                        "read_bytes": 437824,
                        "write_bw": 0.0,
                        "read_bw": 323.60454115421
                    },
                    {
                        "write_bytes": 0,
                        "read_bytes": 501888,
                        "write_bw": 0.0,
                        "read_bw": 363.99556145427647
                    },
                    {
                        "write_bytes": 0,
                        "read_bytes": 480384,
                        "write_bw": 0.0,
                        "read_bw": 325.71498311704164
                    },
                    {
                        "write_bytes": 0,
                        "read_bytes": 488000,
                        "write_bw": 0.0,
                        "read_bw": 364.67168339324013
                    },
                    {
                        "write_bytes": 0,
                        "read_bytes": 495296,
                        "write_bw": 0.0,
                        "read_bw": 365.68593430446754
                    },
                    {
                        "write_bytes": 0,
                        "read_bytes": 505600,
                        "write_bw": 0.0,
                        "read_bw": 379.57103068249216
                    },
                    {
                        "write_bytes": 0,
                        "read_bytes": 293120,
                        "write_bw": 0.0,
                        "read_bw": 192.96397724878872
                    },
                    {
                        "write_bytes": 0,
                        "read_bytes": 0,
                        "write_bw": 0.0,
                        "read_bw": 0.0
                    },
                    {
                        "write_bytes": 0,
                        "read_bytes": 0,
                        "write_bw": 0.0,
                        "read_bw": 0.0
                    },
                    {
                        "write_bytes": 0,
                        "read_bytes": 0,
                        "write_bw": 0.0,
                        "read_bw": 0.0
                    },
                    {
                        "write_bytes": 0,
                        "read_bytes": 0,
                        "write_bw": 0.0,
                        "read_bw": 0.0
                    },
                    {
                        "write_bytes": 0,
                        "read_bytes": 0,
                        "write_bw": 0.0,
                        "read_bw": 0.0
                    },
                    {
                        "write_bytes": 0,
                        "read_bytes": 0,
                        "write_bw": 0.0,
                        "read_bw": 0.0
                    },
                    {
                        "write_bytes": 0,
                        "read_bytes": 248960,
                        "write_bw": 0.0,
                        "read_bw": 171.36681832887066
                    },
                    {
                        "write_bytes": 0,
                        "read_bytes": 360320,
                        "write_bw": 0.0,
                        "read_bw": 251.9737900265037
                    },
                    {
                        "write_bytes": 0,
                        "read_bytes": 107520,
                        "write_bw": 0.0,
                        "read_bw": 71.4480320559251
                    }
                ],
                "overall": {
                    "write_bytes": 0,
                    "read_bytes": 4976512
                }
            },
            "3": {
                "samples": [
                    {
                        "write_bytes": 0,
                        "read_bytes": 296,
                        "write_bw": 0.0,
                        "read_bw": 0.24745025915398766
                    },
                    {
                        "write_bytes": 0,
                        "read_bytes": 0,
                        "write_bw": 0.0,
                        "read_bw": 0.0
                    },
                    {
                        "write_bytes": 0,
                        "read_bytes": 0,
                        "write_bw": 0.0,
                        "read_bw": 0.0
                    },
                    {
                        "write_bytes": 0,
                        "read_bytes": 0,
                        "write_bw": 0.0,
                        "read_bw": 0.0
                    },
                    {
                        "write_bytes": 0,
                        "read_bytes": 0,
                        "write_bw": 0.0,
                        "read_bw": 0.0
                    },
                    {
                        "write_bytes": 0,
                        "read_bytes": 0,
                        "write_bw": 0.0,
                        "read_bw": 0.0
                    },
                    {
                        "write_bytes": 0,
                        "read_bytes": 0,
                        "write_bw": 0.0,
                        "read_bw": 0.0
                    },
                    {
                        "write_bytes": 0,
                        "read_bytes": 0,
                        "write_bw": 0.0,
                        "read_bw": 0.0
                    },
                    {
                        "write_bytes": 0,
                        "read_bytes": 0,
                        "write_bw": 0.0,
                        "read_bw": 0.0
                    },
                    {
                        "write_bytes": 0,
                        "read_bytes": 0,
                        "write_bw": 0.0,
                        "read_bw": 0.0
                    },
                    {
                        "write_bytes": 0,
                        "read_bytes": 0,
                        "write_bw": 0.0,
                        "read_bw": 0.0
                    },
                    {
                        "write_bytes": 0,
                        "read_bytes": 0,
                        "write_bw": 0.0,
                        "read_bw": 0.0
                    },
                    {
                        "write_bytes": 0,
                        "read_bytes": 16,
                        "write_bw": 0.0,
                        "read_bw": 0.010170547366146063
                    },
                    {
                        "write_bytes": 0,
                        "read_bytes": 0,
                        "write_bw": 0.0,
                        "read_bw": 0.0
                    },
                    {
                        "write_bytes": 0,
                        "read_bytes": 0,
                        "write_bw": 0.0,
                        "read_bw": 0.0
                    },
                    {
                        "write_bytes": 0,
                        "read_bytes": 0,
                        "write_bw": 0.0,
                        "read_bw": 0.0
                    },
                    {
                        "write_bytes": 0,
                        "read_bytes": 1712,
                        "write_bw": 0.0,
                        "read_bw": 1.1784222083026452
                    },
                    {
                        "write_bytes": 0,
                        "read_bytes": 0,
                        "write_bw": 0.0,
                        "read_bw": 0.0
                    },
                    {
                        "write_bytes": 0,
                        "read_bytes": 0,
                        "write_bw": 0.0,
                        "read_bw": 0.0
                    }
                ],
                "overall": {
                    "write_bytes": 0,
                    "read_bytes": 2024
                }
            },
            "4": {
                "samples": [
                    {
                        "write_bytes": 0,
                        "read_bytes": 0,
                        "write_bw": 0.0,
                        "read_bw": 0.0
                    },
                    {
                        "write_bytes": 0,
                        "read_bytes": 1024,
                        "write_bw": 0.0,
                        "read_bw": 0.7092542440970515
                    },
                    {
                        "write_bytes": 0,
                        "read_bytes": 512,
                        "write_bw": 0.0,
                        "read_bw": 0.3793351262845162
                    },
                    {
                        "write_bytes": 0,
                        "read_bytes": 1024,
                        "write_bw": 0.0,
                        "read_bw": 0.7568590350047302
                    },
                    {
                        "write_bytes": 0,
                        "read_bytes": 1024,
                        "write_bw": 0.0,
                        "read_bw": 0.7426586308681999
                    },
                    {
                        "write_bytes": 0,
                        "read_bytes": 1024,
                        "write_bw": 0.0,
                        "read_bw": 0.6943031880992094
                    },
                    {
                        "write_bytes": 0,
                        "read_bytes": 1024,
                        "write_bw": 0.0,
                        "read_bw": 0.765212712694012
                    },
                    {
                        "write_bytes": 0,
                        "read_bytes": 768,
                        "write_bw": 0.0,
                        "read_bw": 0.5670281963630457
                    },
                    {
                        "write_bytes": 0,
                        "read_bytes": 768,
                        "write_bw": 0.0,
                        "read_bw": 0.5765635909101147
                    },
                    {
                        "write_bytes": 0,
                        "read_bytes": 1024,
                        "write_bw": 0.0,
                        "read_bw": 0.6741099641879081
                    },
                    {
                        "write_bytes": 0,
                        "read_bytes": 0,
                        "write_bw": 0.0,
                        "read_bw": 0.0
                    },
                    {
                        "write_bytes": 0,
                        "read_bytes": 0,
                        "write_bw": 0.0,
                        "read_bw": 0.0
                    },
                    {
                        "write_bytes": 0,
                        "read_bytes": 407808,
                        "write_bw": 0.0,
                        "read_bw": 259.22691126833087
                    },
                    {
                        "write_bytes": 0,
                        "read_bytes": 425472,
                        "write_bw": 0.0,
                        "read_bw": 297.1525949309625
                    },
                    {
                        "write_bytes": 0,
                        "read_bytes": 430080,
                        "write_bw": 0.0,
                        "read_bw": 301.2334264882015
                    },
                    {
                        "write_bytes": 0,
                        "read_bytes": 342272,
                        "write_bw": 0.0,
                        "read_bw": 233.01245830213088
                    },
                    {
                        "write_bytes": 0,
                        "read_bytes": 896,
                        "write_bw": 0.0,
                        "read_bw": 0.6167443333172723
                    },
                    {
                        "write_bytes": 0,
                        "read_bytes": 896,
                        "write_bw": 0.0,
                        "read_bw": 0.6265778082364213
                    },
                    {
                        "write_bytes": 0,
                        "read_bytes": 896,
                        "write_bw": 0.0,
                        "read_bw": 0.5954002671327092
                    }
                ],
                "overall": {
                    "write_bytes": 0,
                    "read_bytes": 1616512
                }
            },
            "5": {
                "samples": [
                    {
                        "write_bytes": 0,
                        "read_bytes": 0,
                        "write_bw": 0.0,
                        "read_bw": 0.0
                    },
                    {
                        "write_bytes": 36288,
                        "read_bytes": 0,
                        "write_bw": 25.134197275189262,
                        "read_bw": 0.0
                    },
                    {
                        "write_bytes": 38968,
                        "read_bytes": 0,
                        "write_bw": 28.8709593770606,
                        "read_bw": 0.0
                    },
                    {
                        "write_bytes": 50176,
                        "read_bytes": 0,
                        "write_bw": 37.08609271523178,
                        "read_bw": 0.0
                    },
                    {
                        "write_bytes": 50176,
                        "read_bytes": 0,
                        "write_bw": 36.390272912541796,
                        "read_bw": 0.0
                    },
                    {
                        "write_bytes": 50176,
                        "read_bytes": 0,
                        "write_bw": 34.02085621686126,
                        "read_bw": 0.0
                    },
                    {
                        "write_bytes": 50176,
                        "read_bytes": 0,
                        "write_bw": 37.49542292200659,
                        "read_bw": 0.0
                    },
                    {
                        "write_bytes": 25088,
                        "read_bytes": 0,
                        "write_bw": 18.522921081192827,
                        "read_bw": 0.0
                    },
                    {
                        "write_bytes": 50176,
                        "read_bytes": 0,
                        "write_bw": 37.668821272794155,
                        "read_bw": 0.0
                    },
                    {
                        "write_bytes": 50176,
                        "read_bytes": 0,
                        "write_bw": 33.0313882452075,
                        "read_bw": 0.0
                    },
                    {
                        "write_bytes": 0,
                        "read_bytes": 0,
                        "write_bw": 0.0,
                        "read_bw": 0.0
                    },
                    {
                        "write_bytes": 0,
                        "read_bytes": 0,
                        "write_bw": 0.0,
                        "read_bw": 0.0
                    },
                    {
                        "write_bytes": 25088,
                        "read_bytes": 0,
                        "write_bw": 15.947418270117026,
                        "read_bw": 0.0
                    },
                    {
                        "write_bytes": 25088,
                        "read_bytes": 0,
                        "write_bw": 17.521633154773962,
                        "read_bw": 0.0
                    },
                    {
                        "write_bytes": 28224,
                        "read_bytes": 0,
                        "write_bw": 19.768443613288223,
                        "read_bw": 0.0
                    },
                    {
                        "write_bytes": 21952,
                        "read_bytes": 0,
                        "write_bw": 14.944516304717817,
                        "read_bw": 0.0
                    },
                    {
                        "write_bytes": 21952,
                        "read_bytes": 0,
                        "write_bw": 15.110236166273172,
                        "read_bw": 0.0
                    },
                    {
                        "write_bytes": 21952,
                        "read_bytes": 0,
                        "write_bw": 15.351156301792322,
                        "read_bw": 0.0
                    },
                    {
                        "write_bytes": 21952,
                        "read_bytes": 0,
                        "write_bw": 14.587306544751375,
                        "read_bw": 0.0
                    }
                ],
                "overall": {
                    "write_bytes": 567608,
                    "read_bytes": 0
                }
            },
            "total_samples": 19
        }
    ]
}